pagermaid/__init__.py
pagermaid/__main__.py
pagermaid/listener.py
pagermaid/utils.py
pagermaid/assets/Impact-Regular.ttf
pagermaid/assets/caption-gif.sh
pagermaid/assets/caption.sh
pagermaid/assets/config.gen.yml
pagermaid/assets/graffiti.flf
pagermaid/assets/pagermaid
pagermaid/assets/replacements.json
pagermaid/interface/__init__.py
pagermaid/interface/__main__.py
pagermaid/interface/forms.py
pagermaid/interface/modals.py
pagermaid/interface/views.py
pagermaid/modules/__init__.py
pagermaid/modules/account.py
pagermaid/modules/avoid.py
pagermaid/modules/captions.py
pagermaid/modules/clock.py
pagermaid/modules/external.py
pagermaid/modules/fun.py
pagermaid/modules/help.py
pagermaid/modules/message.py
pagermaid/modules/plugin.py
pagermaid/modules/prune.py
pagermaid/modules/qr.py
pagermaid/modules/status.py
pagermaid/modules/sticker.py
pagermaid/modules/system.py
pagermaid/modules/update.py
pagermaid-2020.2.post13.dist-info/LICENSE
pagermaid-2020.2.post13.dist-info/METADATA
pagermaid-2020.2.post13.dist-info/WHEEL
pagermaid-2020.2.post13.dist-info/entry_points.txt
pagermaid-2020.2.post13.dist-info/top_level.txt
pagermaid-2020.2.post13.dist-info/RECORD
