Metadata-Version: 2.1
Name: pagermaid
Version: 2020.2.post13
Summary: A telegram utility daemon and plugin framework.
Home-page: https://katonkeyboard.moe/pagermaid.html
Author: Stykers
Author-email: stykers@stykers.moe
License: UNKNOWN
Platform: UNKNOWN
Classifier: Programming Language :: Python :: 3
Classifier: License :: OSI Approved :: GNU General Public License v3 or later (GPLv3+)
Classifier: Operating System :: Unix
Requires-Python: >=3.6
Requires-Dist: psutil
Requires-Dist: pyqrcode
Requires-Dist: pypng
Requires-Dist: pyzbar
Requires-Dist: emoji
Requires-Dist: youtube-dl
Requires-Dist: pyyaml
Requires-Dist: redis
Requires-Dist: coloredlogs
Requires-Dist: requests
Requires-Dist: pytz
Requires-Dist: cowpy
Requires-Dist: googletrans
Requires-Dist: beautifulsoup4
Requires-Dist: gtts
Requires-Dist: gtts-token
Requires-Dist: wordcloud
Requires-Dist: telethon
Requires-Dist: pillow
Requires-Dist: python-magic
Requires-Dist: pygments
Requires-Dist: distutils2-py3
Requires-Dist: speedtest-cli
Requires-Dist: gitpython
Requires-Dist: werkzeug
Requires-Dist: flask
Requires-Dist: flask-sqlalchemy
Requires-Dist: flask-login
Requires-Dist: flask-bcrypt
Requires-Dist: flask-wtf
Requires-Dist: wtforms
Requires-Dist: cheroot
